{"assignees":[],"body":"## Why this matters\n\n`projectbluefin/bluespeed` already implies three homelab host roles — NAS, media server, and general-purpose server — but this repo does not yet define what those roles must prove in the lab. We need a first issue that turns those role ideas into testable storage and persistence expectations.\n\n## Scope\n\nDefine the first role/storage validation lane under #52:\n\n- establish the initial role matrix for NAS, media-server, and general-purpose-server validation\n- define the storage and state paths each role must preserve across reboot/update cycles\n- call out where the current lab can validate the contract directly and where it needs blocker issues for shared-storage or RWX assumptions\n- include the first storage observability hooks that materially affect role validation\n\n## Acceptance criteria\n\n- [ ] The first role matrix is defined for NAS, media server, and general-purpose server assumptions\n- [ ] Each role lists the minimum storage/persistence behavior that must be validated\n- [ ] Shared-storage or RWX gaps are surfaced explicitly instead of left implicit\n- [ ] The lane is framed as validation of bluespeed role ideas, not as a replacement source of truth for them\n\n## Links\n\n- Child of #52\n- Source ideas: `projectbluefin/bluespeed#7`, `projectbluefin/bluespeed#9`","labels":[{"id":"LA_kwDOSnvXMs8AAAACkr8dDw","name":"enhancement","description":"New feature or request","color":"a2eeef"}],"number":57,"state":"OPEN","title":"feat: define homelab role matrix and storage-persistence contract"}
