{
  "schema_version": 1,
  "_meta": {
    "page": "index",
    "description": "BuildStream / remote-execution cache usage across both cache drives (ghost, exo-0)",
    "generated_at": "2026-07-04T00:07:03Z",
    "starter_artifact": false,
    "status": "live"
  },
  "summary_metrics": [],
  "rows": [
    {
      "id": "bazel-remote-ghost",
      "node": "ghost",
      "drive": "/var/mnt/ghost-data",
      "cache_backend": "bazel-remote",
      "storage_type": "cas",
      "used_bytes": 403597967,
      "capacity_bytes": 2147483648000,
      "percent": 0.019,
      "source_url": "http://192.168.1.102:32746 (kubectl proxy: services/bst-artifact-server:8080/proxy/status)",
      "collected_at": "2026-07-04T00:07:03Z",
      "derivation": "live /status endpoint (CurrSize / MaxSize) via kubectl API-server service proxy",
      "state": "available",
      "state_reason": null
    },
    {
      "id": "buildbarn-storage-0-cas",
      "node": "exo-0",
      "drive": "/var/mnt/ghost-data",
      "cache_backend": "buildbarn",
      "storage_type": "cas",
      "used_bytes": 0.0,
      "capacity_bytes": 21474836480,
      "percent": 0.0,
      "source_url": "kubectl proxy: pods/storage-0:9980/proxy/metrics (namespace buildbarn)",
      "collected_at": "2026-07-04T00:07:03Z",
      "derivation": "(allocations_total - releases_total) * block_size, where block_size = 21474836480 bytes / 35 blocks (manifests/buildbarn-config.yaml); block-device-backed storage is fixed-size on disk, so this is an estimate of logical fill, not physical allocation",
      "state": "available",
      "state_reason": null
    },
    {
      "id": "buildbarn-storage-0-ac",
      "node": "exo-0",
      "drive": "/var/mnt/ghost-data",
      "cache_backend": "buildbarn",
      "storage_type": "ac",
      "used_bytes": 0.0,
      "capacity_bytes": 20971520,
      "percent": 0.0,
      "source_url": "kubectl proxy: pods/storage-0:9980/proxy/metrics (namespace buildbarn)",
      "collected_at": "2026-07-04T00:07:03Z",
      "derivation": "(allocations_total - releases_total) * block_size, where block_size = 20971520 bytes / 33 blocks (manifests/buildbarn-config.yaml); block-device-backed storage is fixed-size on disk, so this is an estimate of logical fill, not physical allocation",
      "state": "available",
      "state_reason": null
    },
    {
      "id": "buildbarn-storage-1-cas",
      "node": "ghost",
      "drive": "/var/mnt/ghost-data",
      "cache_backend": "buildbarn",
      "storage_type": "cas",
      "used_bytes": 0.0,
      "capacity_bytes": 21474836480,
      "percent": 0.0,
      "source_url": "kubectl proxy: pods/storage-1:9980/proxy/metrics (namespace buildbarn)",
      "collected_at": "2026-07-04T00:07:03Z",
      "derivation": "(allocations_total - releases_total) * block_size, where block_size = 21474836480 bytes / 35 blocks (manifests/buildbarn-config.yaml); block-device-backed storage is fixed-size on disk, so this is an estimate of logical fill, not physical allocation",
      "state": "available",
      "state_reason": null
    },
    {
      "id": "buildbarn-storage-1-ac",
      "node": "ghost",
      "drive": "/var/mnt/ghost-data",
      "cache_backend": "buildbarn",
      "storage_type": "ac",
      "used_bytes": 0.0,
      "capacity_bytes": 20971520,
      "percent": 0.0,
      "source_url": "kubectl proxy: pods/storage-1:9980/proxy/metrics (namespace buildbarn)",
      "collected_at": "2026-07-04T00:07:03Z",
      "derivation": "(allocations_total - releases_total) * block_size, where block_size = 20971520 bytes / 33 blocks (manifests/buildbarn-config.yaml); block-device-backed storage is fixed-size on disk, so this is an estimate of logical fill, not physical allocation",
      "state": "available",
      "state_reason": null
    }
  ]
}
